comicgeeks/Comic_Geeks.py
comicgeeks/__init__.py
comicgeeks/__version__.py
comicgeeks/classes.py
comicgeeks/extract.py
comicgeeks/test.py
comicgeeks/utils.py
comicgeeks-0.3.4.dist-info/LICENSE.txt
comicgeeks-0.3.4.dist-info/METADATA
comicgeeks-0.3.4.dist-info/WHEEL
comicgeeks-0.3.4.dist-info/top_level.txt
comicgeeks-0.3.4.dist-info/RECORD
