Metadata-Version: 2.1
Name: comicgeeks
Version: 0.3.4
Summary: A python client for League of Comics Geeks.
Home-page: https://github.com/pruizlezcano/comicgeeks
Author: Pablo Ruiz
Author-email: pruizlezcano@gmail.com
License: GPL-3.0-only
Project-URL: Documentation, https://comicgeeks.readthedocs.io
Project-URL: Source, https://github.com/pruizlezcano/comicgeeks
Project-URL: Changelog, https://comicgeeks.readthedocs.io/en/latest/changelog.html
Project-URL: Tracker, https://github.com/pruizlezcano/comicgeeks/issues
Platform: any
Classifier: Development Status :: 4 - Beta
Classifier: Programming Language :: Python
Classifier: Topic :: Internet :: WWW/HTTP :: Indexing/Search
License-File: LICENSE.txt
Requires-Dist: beautifulsoup4 <5.0.0,>=4.11.1
Requires-Dist: lxml <5.0.0,>=4.9.1
Requires-Dist: requests <3.0.0,>=2.28.1
Requires-Dist: importlib-metadata ; python_version < "3.8"
Provides-Extra: development
Requires-Dist: black ; extra == 'development'
Requires-Dist: commitizen ; extra == 'development'
Requires-Dist: flake8 ; extra == 'development'
Requires-Dist: pre-commit ; extra == 'development'
Provides-Extra: docs
Requires-Dist: myst-parser ; extra == 'docs'
Requires-Dist: Sphinx ; extra == 'docs'
Provides-Extra: testing
Requires-Dist: setuptools ; extra == 'testing'
Requires-Dist: pytest ; extra == 'testing'
Requires-Dist: pytest-cov ; extra == 'testing'
Requires-Dist: python-dotenv ; extra == 'testing'
